fpga/uart/uart.v
`default_nettype none

module uart
#(
    parameter DELAY_FRAMES = 234 // 27,000,000 (27Mhz) / 115200 Baud rate
)
(
    input clk,
    input uart_rx,
    output uart_tx,
    output reg [5:0] led,
    input btn1
);

localparam HALF_DELAY_WAIT = (DELAY_FRAMES / 2);

reg [3:0] rxState = 0;
reg [12:0] rxCounter = 0;
reg [7:0] dataIn = 0;
reg [2:0] rxBitNumber = 0;
reg byteReady = 0;

localparam RX_STATE_IDLE = 0;
localparam RX_STATE_START_BIT = 1;
localparam RX_STATE_READ_WAIT = 2;
localparam RX_STATE_READ = 3;
localparam RX_STATE_STOP_BIT = 5;

always @(posedge clk) begin
    case (rxState)
        RX_STATE_IDLE: begin
            if (uart_rx == 0) begin
                rxState <= RX_STATE_START_BIT;
                rxCounter <= 1;
                rxBitNumber <= 0;
                byteReady <= 0;
            end
        end 
        RX_STATE_START_BIT: begin
            if (rxCounter == HALF_DELAY_WAIT) begin
                rxState <= RX_STATE_READ_WAIT;
                rxCounter <= 1;
            end else 
                rxCounter <= rxCounter + 1;
        end
        RX_STATE_READ_WAIT: begin
            rxCounter <= rxCounter + 1;
            if ((rxCounter + 1) == DELAY_FRAMES) begin
                rxState <= RX_STATE_READ;
            end
        end
        RX_STATE_READ: begin
            rxCounter <= 1;
            dataIn <= {uart_rx, dataIn[7:1]};
            rxBitNumber <= rxBitNumber + 1;
            if (rxBitNumber == 3'b111)
                rxState <= RX_STATE_STOP_BIT;
            else
                rxState <= RX_STATE_READ_WAIT;
        end
        RX_STATE_STOP_BIT: begin
            rxCounter <= rxCounter + 1;
            if ((rxCounter + 1) == DELAY_FRAMES) begin
                rxState <= RX_STATE_IDLE;
                rxCounter <= 0;
                byteReady <= 1;
            end
        end
    endcase
end

always @(posedge clk) begin
    if (byteReady) begin
        led <= ~dataIn[5:0];
//        led <= dataIn[5:0];
    end
    else begin
        led <= 6'b010101;
    end
end

reg [3:0] txState = 0;
reg [24:0] txCounter = 0;
reg [7:0] dataOut = 0;
reg txPinRegister = 1;
reg [2:0] txBitNumber = 0;
reg [3:0] txByteCounter = 0;

assign uart_tx = txPinRegister;

localparam MEMORY_LENGTH = 12;
reg [7:0] testMemory [MEMORY_LENGTH-1:0];

initial begin
    testMemory[0] = "L";
    testMemory[1] = "u";
    testMemory[2] = "s";
    testMemory[3] = "h";
    testMemory[4] = "a";
    testMemory[5] = "y";
    testMemory[6] = " ";
    testMemory[7] = "L";
    testMemory[8] = "a";
    testMemory[9] = "b";
    testMemory[10] = "s";
    testMemory[11] = " ";
end

localparam TX_STATE_IDLE = 0;
localparam TX_STATE_START_BIT = 1;
localparam TX_STATE_WRITE = 2;
localparam TX_STATE_STOP_BIT = 3;
localparam TX_STATE_DEBOUNCE = 4;

always @(posedge clk) begin
    case (txState)
        TX_STATE_IDLE: begin
            if (btn1 == 0) begin
                txState <= TX_STATE_START_BIT;
                txCounter <= 0;
                txByteCounter <= 0;
            end
            else begin
                txPinRegister <= 1;
            end
        end 
        TX_STATE_START_BIT: begin
            txPinRegister <= 0;
            if ((txCounter + 1) == DELAY_FRAMES) begin
                txState <= TX_STATE_WRITE;
                dataOut <= testMemory[txByteCounter];
                txBitNumber <= 0;
                txCounter <= 0;
            end else 
                txCounter <= txCounter + 1;
        end
        TX_STATE_WRITE: begin
            txPinRegister <= dataOut[txBitNumber];
            if ((txCounter + 1) == DELAY_FRAMES) begin
                if (txBitNumber == 3'b111) begin
                    txState <= TX_STATE_STOP_BIT;
                end else begin
                    txState <= TX_STATE_WRITE;
                    txBitNumber <= txBitNumber + 1;
                end
                txCounter <= 0;
            end else 
                txCounter <= txCounter + 1;
        end
        TX_STATE_STOP_BIT: begin
            txPinRegister <= 1;
            if ((txCounter + 1) == DELAY_FRAMES) begin
                if (txByteCounter == MEMORY_LENGTH - 1) begin
                    txState <= TX_STATE_DEBOUNCE;
                end else begin
                    txByteCounter <= txByteCounter + 1;
                    txState <= TX_STATE_START_BIT;
                end
                txCounter <= 0;
            end else 
                txCounter <= txCounter + 1;
        end
        TX_STATE_DEBOUNCE: begin
            if (txCounter == 23'b111111111111111111) begin
                if (btn1 == 1) 
                    txState <= TX_STATE_IDLE;
            end else
                txCounter <= txCounter + 1;
        end
    endcase      
end
endmodule

fpga/uart/uart_tb.v
module test();
  reg clk = 0;
  reg uart_rx = 1;
  wire uart_tx;
  wire [5:0] led;
  reg btn = 1;

  uart #(8'd8) u(
    clk,
    uart_rx,
    uart_tx,
    led,
    btn
  );

  always
    #1  clk = ~clk;

  initial begin
    $display("Starting UART RX");
    $monitor("LED Value %b", led);
    #10 uart_rx=0;
    #16 uart_rx=1;
    #16 uart_rx=0;
    #16 uart_rx=0;
    #16 uart_rx=0;
    #16 uart_rx=0;
    #16 uart_rx=1;
    #16 uart_rx=1;
    #16 uart_rx=0;
    #16 uart_rx=1;
    #4 btn=0;
    #4 btn=1;
    #1000 $finish;
  end

  initial begin
    $dumpfile("uart.vcd");
    $dumpvars(0,test);
  end
endmodule

fpga/uart/uart.vcd
$date
	Sun Mar 26 00:02:41 2023
$end
$version
	Icarus Verilog
$end
$timescale
	1s
$end
$scope module test $end
$var wire 1 ! uart_tx $end
$var wire 6 " led [5:0] $end
$var reg 1 # btn $end
$var reg 1 $ clk $end
$var reg 1 % uart_rx $end
$scope module u $end
$var wire 1 # btn1 $end
$var wire 1 $ clk $end
$var wire 1 % uart_rx $end
$var wire 1 ! uart_tx $end
$var parameter 8 & DELAY_FRAMES $end
$var parameter 32 ' HALF_DELAY_WAIT $end
$var parameter 32 ( MEMORY_LENGTH $end
$var parameter 32 ) RX_STATE_IDLE $end
$var parameter 32 * RX_STATE_READ $end
$var parameter 32 + RX_STATE_READ_WAIT $end
$var parameter 32 , RX_STATE_START_BIT $end
$var parameter 32 - RX_STATE_STOP_BIT $end
$var parameter 32 . TX_STATE_DEBOUNCE $end
$var parameter 32 / TX_STATE_IDLE $end
$var parameter 32 0 TX_STATE_START_BIT $end
$var parameter 32 1 TX_STATE_STOP_BIT $end
$var parameter 32 2 TX_STATE_WRITE $end
$var reg 1 3 byteReady $end
$var reg 8 4 dataIn [7:0] $end
$var reg 8 5 dataOut [7:0] $end
$var reg 6 6 led [5:0] $end
$var reg 3 7 rxBitNumber [2:0] $end
$var reg 13 8 rxCounter [12:0] $end
$var reg 4 9 rxState [3:0] $end
$var reg 3 : txBitNumber [2:0] $end
$var reg 4 ; txByteCounter [3:0] $end
$var reg 25 < txCounter [24:0] $end
$var reg 1 = txPinRegister $end
$var reg 4 > txState [3:0] $end
$upscope $end
$upscope $end
$enddefinitions $end
$comment Show the parameter values. $end
$dumpall
b10 2
b11 1
b1 0
b0 /
b100 .
b101 -
b1 ,
b10 +
b11 *
b0 )
b1100 (
b100 '
b1000 &
$end
#0
$dumpvars
b0 >
1=
b0 <
b0 ;
b0 :
b0 9
b0 8
b0 7
bx 6
b0 5
b0 4
03
1%
0$
1#
bx "
1!
$end
#1
1$
#2
0$
#3
1$
#4
0$
#5
1$
#6
0$
#7
1$
#8
0$
#9
1$
#10
0$
0%
#11
b1 8
b1 9
1$
#12
0$
#13
b10 8
1$
#14
0$
#15
b11 8
1$
#16
0$
#17
b100 8
1$
#18
0$
#19
b1 8
b10 9
1$
#20
0$
#21
b10 8
1$
#22
0$
#23
b11 8
1$
#24
0$
#25
b100 8
1$
#26
0$
1%
#27
b101 8
1$
#28
0$
#29
b110 8
1$
#30
0$
#31
b111 8
1$
#32
0$
#33
b11 9
b1000 8
1$
#34
0$
#35
b10 9
b1 7
b10000000 4
b1 8
1$
#36
0$
#37
b10 8
1$
#38
0$
#39
b11 8
1$
#40
0$
#41
b100 8
1$
#42
0$
0%
#43
b101 8
1$
#44
0$
#45
b110 8
1$
#46
0$
#47
b111 8
1$
#48
0$
#49
b11 9
b1000 8
1$
#50
0$
#51
b10 9
b10 7
b1000000 4
b1 8
1$
#52
0$
#53
b10 8
1$
#54
0$
#55
b11 8
1$
#56
0$
#57
b100 8
1$
#58
0$
#59
b101 8
1$
#60
0$
#61
b110 8
1$
#62
0$
#63
b111 8
1$
#64
0$
#65
b11 9
b1000 8
1$
#66
0$
#67
b10 9
b11 7
b100000 4
b1 8
1$
#68
0$
#69
b10 8
1$
#70
0$
#71
b11 8
1$
#72
0$
#73
b100 8
1$
#74
0$
#75
b101 8
1$
#76
0$
#77
b110 8
1$
#78
0$
#79
b111 8
1$
#80
0$
#81
b11 9
b1000 8
1$
#82
0$
#83
b10 9
b100 7
b10000 4
b1 8
1$
#84
0$
#85
b10 8
1$
#86
0$
#87
b11 8
1$
#88
0$
#89
b100 8
1$
#90
0$
#91
b101 8
1$
#92
0$
#93
b110 8
1$
#94
0$
#95
b111 8
1$
#96
0$
#97
b11 9
b1000 8
1$
#98
0$
#99
b10 9
b101 7
b1000 4
b1 8
1$
#100
0$
#101
b10 8
1$
#102
0$
#103
b11 8
1$
#104
0$
#105
b100 8
1$
#106
0$
1%
#107
b101 8
1$
#108
0$
#109
b110 8
1$
#110
0$
#111
b111 8
1$
#112
0$
#113
b11 9
b1000 8
1$
#114
0$
#115
b10 9
b110 7
b10000100 4
b1 8
1$
#116
0$
#117
b10 8
1$
#118
0$
#119
b11 8
1$
#120
0$
#121
b100 8
1$
#122
0$
#123
b101 8
1$
#124
0$
#125
b110 8
1$
#126
0$
#127
b111 8
1$
#128
0$
#129
b11 9
b1000 8
1$
#130
0$
#131
b10 9
b111 7
b11000010 4
b1 8
1$
#132
0$
#133
b10 8
1$
#134
0$
#135
b11 8
1$
#136
0$
#137
b100 8
1$
#138
0$
0%
#139
b101 8
1$
#140
0$
#141
b110 8
1$
#142
0$
#143
b111 8
1$
#144
0$
#145
b11 9
b1000 8
1$
#146
0$
#147
b101 9
b0 7
b1100001 4
b1 8
1$
#148
0$
#149
b10 8
1$
#150
0$
#151
b11 8
1$
#152
0$
#153
b100 8
1$
#154
0$
1%
#155
b101 8
1$
#156
0$
#157
b110 8
1$
#158
0$
0#
#159
b1 >
b111 8
1$
#160
0$
#161
13
b0 9
b0 8
b1 <
0!
0=
1$
#162
0$
1#
#163
b10 <
b11110 "
b11110 6
1$
#164
0$
#165
b11 <
1$
#166
0$
#167
b100 <
1$
#168
0$
#169
b101 <
1$
#170
0$
#171
b110 <
1$
#172
0$
#173
b111 <
1$
#174
0$
#175
b0 <
b1001100 5
b10 >
1$
#176
0$
#177
b1 <
1$
#178
0$
#179
b10 <
1$
#180
0$
#181
b11 <
1$
#182
0$
#183
b100 <
1$
#184
0$
#185
b101 <
1$
#186
0$
#187
b110 <
1$
#188
0$
#189
b111 <
1$
#190
0$
#191
b0 <
b1 :
1$
#192
0$
#193
b1 <
1$
#194
0$
#195
b10 <
1$
#196
0$
#197
b11 <
1$
#198
0$
#199
b100 <
1$
#200
0$
#201
b101 <
1$
#202
0$
#203
b110 <
1$
#204
0$
#205
b111 <
1$
#206
0$
#207
b0 <
b10 :
1$
#208
0$
#209
b1 <
1!
1=
1$
#210
0$
#211
b10 <
1$
#212
0$
#213
b11 <
1$
#214
0$
#215
b100 <
1$
#216
0$
#217
b101 <
1$
#218
0$
#219
b110 <
1$
#220
0$
#221
b111 <
1$
#222
0$
#223
b0 <
b11 :
1$
#224
0$
#225
b1 <
1$
#226
0$
#227
b10 <
1$
#228
0$
#229
b11 <
1$
#230
0$
#231
b100 <
1$
#232
0$
#233
b101 <
1$
#234
0$
#235
b110 <
1$
#236
0$
#237
b111 <
1$
#238
0$
#239
b0 <
b100 :
1$
#240
0$
#241
b1 <
0!
0=
1$
#242
0$
#243
b10 <
1$
#244
0$
#245
b11 <
1$
#246
0$
#247
b100 <
1$
#248
0$
#249
b101 <
1$
#250
0$
#251
b110 <
1$
#252
0$
#253
b111 <
1$
#254
0$
#255
b0 <
b101 :
1$
#256
0$
#257
b1 <
1$
#258
0$
#259
b10 <
1$
#260
0$
#261
b11 <
1$
#262
0$
#263
b100 <
1$
#264
0$
#265
b101 <
1$
#266
0$
#267
b110 <
1$
#268
0$
#269
b111 <
1$
#270
0$
#271
b0 <
b110 :
1$
#272
0$
#273
b1 <
1!
1=
1$
#274
0$
#275
b10 <
1$
#276
0$
#277
b11 <
1$
#278
0$
#279
b100 <
1$
#280
0$
#281
b101 <
1$
#282
0$
#283
b110 <
1$
#284
0$
#285
b111 <
1$
#286
0$
#287
b0 <
b111 :
1$
#288
0$
#289
b1 <
0!
0=
1$
#290
0$
#291
b10 <
1$
#292
0$
#293
b11 <
1$
#294
0$
#295
b100 <
1$
#296
0$
#297
b101 <
1$
#298
0$
#299
b110 <
1$
#300
0$
#301
b111 <
1$
#302
0$
#303
b0 <
b11 >
1$
#304
0$
#305
b1 <
1!
1=
1$
#306
0$
#307
b10 <
1$
#308
0$
#309
b11 <
1$
#310
0$
#311
b100 <
1$
#312
0$
#313
b101 <
1$
#314
0$
#315
b110 <
1$
#316
0$
#317
b111 <
1$
#318
0$
#319
b0 <
b1 >
b1 ;
1$
#320
0$
#321
b1 <
0!
0=
1$
#322
0$
#323
b10 <
1$
#324
0$
#325
b11 <
1$
#326
0$
#327
b100 <
1$
#328
0$
#329
b101 <
1$
#330
0$
#331
b110 <
1$
#332
0$
#333
b111 <
1$
#334
0$
#335
b0 <
b0 :
b1110101 5
b10 >
1$
#336
0$
#337
b1 <
1!
1=
1$
#338
0$
#339
b10 <
1$
#340
0$
#341
b11 <
1$
#342
0$
#343
b100 <
1$
#344
0$
#345
b101 <
1$
#346
0$
#347
b110 <
1$
#348
0$
#349
b111 <
1$
#350
0$
#351
b0 <
b1 :
1$
#352
0$
#353
b1 <
0!
0=
1$
#354
0$
#355
b10 <
1$
#356
0$
#357
b11 <
1$
#358
0$
#359
b100 <
1$
#360
0$
#361
b101 <
1$
#362
0$
#363
b110 <
1$
#364
0$
#365
b111 <
1$
#366
0$
#367
b0 <
b10 :
1$
#368
0$
#369
b1 <
1!
1=
1$
#370
0$
#371
b10 <
1$
#372
0$
#373
b11 <
1$
#374
0$
#375
b100 <
1$
#376
0$
#377
b101 <
1$
#378
0$
#379
b110 <
1$
#380
0$
#381
b111 <
1$
#382
0$
#383
b0 <
b11 :
1$
#384
0$
#385
b1 <
0!
0=
1$
#386
0$
#387
b10 <
1$
#388
0$
#389
b11 <
1$
#390
0$
#391
b100 <
1$
#392
0$
#393
b101 <
1$
#394
0$
#395
b110 <
1$
#396
0$
#397
b111 <
1$
#398
0$
#399
b0 <
b100 :
1$
#400
0$
#401
b1 <
1!
1=
1$
#402
0$
#403
b10 <
1$
#404
0$
#405
b11 <
1$
#406
0$
#407
b100 <
1$
#408
0$
#409
b101 <
1$
#410
0$
#411
b110 <
1$
#412
0$
#413
b111 <
1$
#414
0$
#415
b0 <
b101 :
1$
#416
0$
#417
b1 <
1$
#418
0$
#419
b10 <
1$
#420
0$
#421
b11 <
1$
#422
0$
#423
b100 <
1$
#424
0$
#425
b101 <
1$
#426
0$
#427
b110 <
1$
#428
0$
#429
b111 <
1$
#430
0$
#431
b0 <
b110 :
1$
#432
0$
#433
b1 <
1$
#434
0$
#435
b10 <
1$
#436
0$
#437
b11 <
1$
#438
0$
#439
b100 <
1$
#440
0$
#441
b101 <
1$
#442
0$
#443
b110 <
1$
#444
0$
#445
b111 <
1$
#446
0$
#447
b0 <
b111 :
1$
#448
0$
#449
b1 <
0!
0=
1$
#450
0$
#451
b10 <
1$
#452
0$
#453
b11 <
1$
#454
0$
#455
b100 <
1$
#456
0$
#457
b101 <
1$
#458
0$
#459
b110 <
1$
#460
0$
#461
b111 <
1$
#462
0$
#463
b0 <
b11 >
1$
#464
0$
#465
b1 <
1!
1=
1$
#466
0$
#467
b10 <
1$
#468
0$
#469
b11 <
1$
#470
0$
#471
b100 <
1$
#472
0$
#473
b101 <
1$
#474
0$
#475
b110 <
1$
#476
0$
#477
b111 <
1$
#478
0$
#479
b0 <
b1 >
b10 ;
1$
#480
0$
#481
b1 <
0!
0=
1$
#482
0$
#483
b10 <
1$
#484
0$
#485
b11 <
1$
#486
0$
#487
b100 <
1$
#488
0$
#489
b101 <
1$
#490
0$
#491
b110 <
1$
#492
0$
#493
b111 <
1$
#494
0$
#495
b0 <
b0 :
b1110011 5
b10 >
1$
#496
0$
#497
b1 <
1!
1=
1$
#498
0$
#499
b10 <
1$
#500
0$
#501
b11 <
1$
#502
0$
#503
b100 <
1$
#504
0$
#505
b101 <
1$
#506
0$
#507
b110 <
1$
#508
0$
#509
b111 <
1$
#510
0$
#511
b0 <
b1 :
1$
#512
0$
#513
b1 <
1$
#514
0$
#515
b10 <
1$
#516
0$
#517
b11 <
1$
#518
0$
#519
b100 <
1$
#520
0$
#521
b101 <
1$
#522
0$
#523
b110 <
1$
#524
0$
#525
b111 <
1$
#526
0$
#527
b0 <
b10 :
1$
#528
0$
#529
b1 <
0!
0=
1$
#530
0$
#531
b10 <
1$
#532
0$
#533
b11 <
1$
#534
0$
#535
b100 <
1$
#536
0$
#537
b101 <
1$
#538
0$
#539
b110 <
1$
#540
0$
#541
b111 <
1$
#542
0$
#543
b0 <
b11 :
1$
#544
0$
#545
b1 <
1$
#546
0$
#547
b10 <
1$
#548
0$
#549
b11 <
1$
#550
0$
#551
b100 <
1$
#552
0$
#553
b101 <
1$
#554
0$
#555
b110 <
1$
#556
0$
#557
b111 <
1$
#558
0$
#559
b0 <
b100 :
1$
#560
0$
#561
b1 <
1!
1=
1$
#562
0$
#563
b10 <
1$
#564
0$
#565
b11 <
1$
#566
0$
#567
b100 <
1$
#568
0$
#569
b101 <
1$
#570
0$
#571
b110 <
1$
#572
0$
#573
b111 <
1$
#574
0$
#575
b0 <
b101 :
1$
#576
0$
#577
b1 <
1$
#578
0$
#579
b10 <
1$
#580
0$
#581
b11 <
1$
#582
0$
#583
b100 <
1$
#584
0$
#585
b101 <
1$
#586
0$
#587
b110 <
1$
#588
0$
#589
b111 <
1$
#590
0$
#591
b0 <
b110 :
1$
#592
0$
#593
b1 <
1$
#594
0$
#595
b10 <
1$
#596
0$
#597
b11 <
1$
#598
0$
#599
b100 <
1$
#600
0$
#601
b101 <
1$
#602
0$
#603
b110 <
1$
#604
0$
#605
b111 <
1$
#606
0$
#607
b0 <
b111 :
1$
#608
0$
#609
b1 <
0!
0=
1$
#610
0$
#611
b10 <
1$
#612
0$
#613
b11 <
1$
#614
0$
#615
b100 <
1$
#616
0$
#617
b101 <
1$
#618
0$
#619
b110 <
1$
#620
0$
#621
b111 <
1$
#622
0$
#623
b0 <
b11 >
1$
#624
0$
#625
b1 <
1!
1=
1$
#626
0$
#627
b10 <
1$
#628
0$
#629
b11 <
1$
#630
0$
#631
b100 <
1$
#632
0$
#633
b101 <
1$
#634
0$
#635
b110 <
1$
#636
0$
#637
b111 <
1$
#638
0$
#639
b0 <
b1 >
b11 ;
1$
#640
0$
#641
b1 <
0!
0=
1$
#642
0$
#643
b10 <
1$
#644
0$
#645
b11 <
1$
#646
0$
#647
b100 <
1$
#648
0$
#649
b101 <
1$
#650
0$
#651
b110 <
1$
#652
0$
#653
b111 <
1$
#654
0$
#655
b0 <
b0 :
b1101000 5
b10 >
1$
#656
0$
#657
b1 <
1$
#658
0$
#659
b10 <
1$
#660
0$
#661
b11 <
1$
#662
0$
#663
b100 <
1$
#664
0$
#665
b101 <
1$
#666
0$
#667
b110 <
1$
#668
0$
#669
b111 <
1$
#670
0$
#671
b0 <
b1 :
1$
#672
0$
#673
b1 <
1$
#674
0$
#675
b10 <
1$
#676
0$
#677
b11 <
1$
#678
0$
#679
b100 <
1$
#680
0$
#681
b101 <
1$
#682
0$
#683
b110 <
1$
#684
0$
#685
b111 <
1$
#686
0$
#687
b0 <
b10 :
1$
#688
0$
#689
b1 <
1$
#690
0$
#691
b10 <
1$
#692
0$
#693
b11 <
1$
#694
0$
#695
b100 <
1$
#696
0$
#697
b101 <
1$
#698
0$
#699
b110 <
1$
#700
0$
#701
b111 <
1$
#702
0$
#703
b0 <
b11 :
1$
#704
0$
#705
b1 <
1!
1=
1$
#706
0$
#707
b10 <
1$
#708
0$
#709
b11 <
1$
#710
0$
#711
b100 <
1$
#712
0$
#713
b101 <
1$
#714
0$
#715
b110 <
1$
#716
0$
#717
b111 <
1$
#718
0$
#719
b0 <
b100 :
1$
#720
0$
#721
b1 <
0!
0=
1$
#722
0$
#723
b10 <
1$
#724
0$
#725
b11 <
1$
#726
0$
#727
b100 <
1$
#728
0$
#729
b101 <
1$
#730
0$
#731
b110 <
1$
#732
0$
#733
b111 <
1$
#734
0$
#735
b0 <
b101 :
1$
#736
0$
#737
b1 <
1!
1=
1$
#738
0$
#739
b10 <
1$
#740
0$
#741
b11 <
1$
#742
0$
#743
b100 <
1$
#744
0$
#745
b101 <
1$
#746
0$
#747
b110 <
1$
#748
0$
#749
b111 <
1$
#750
0$
#751
b0 <
b110 :
1$
#752
0$
#753
b1 <
1$
#754
0$
#755
b10 <
1$
#756
0$
#757
b11 <
1$
#758
0$
#759
b100 <
1$
#760
0$
#761
b101 <
1$
#762
0$
#763
b110 <
1$
#764
0$
#765
b111 <
1$
#766
0$
#767
b0 <
b111 :
1$
#768
0$
#769
b1 <
0!
0=
1$
#770
0$
#771
b10 <
1$
#772
0$
#773
b11 <
1$
#774
0$
#775
b100 <
1$
#776
0$
#777
b101 <
1$
#778
0$
#779
b110 <
1$
#780
0$
#781
b111 <
1$
#782
0$
#783
b0 <
b11 >
1$
#784
0$
#785
b1 <
1!
1=
1$
#786
0$
#787
b10 <
1$
#788
0$
#789
b11 <
1$
#790
0$
#791
b100 <
1$
#792
0$
#793
b101 <
1$
#794
0$
#795
b110 <
1$
#796
0$
#797
b111 <
1$
#798
0$
#799
b0 <
b1 >
b100 ;
1$
#800
0$
#801
b1 <
0!
0=
1$
#802
0$
#803
b10 <
1$
#804
0$
#805
b11 <
1$
#806
0$
#807
b100 <
1$
#808
0$
#809
b101 <
1$
#810
0$
#811
b110 <
1$
#812
0$
#813
b111 <
1$
#814
0$
#815
b0 <
b0 :
b1100001 5
b10 >
1$
#816
0$
#817
b1 <
1!
1=
1$
#818
0$
#819
b10 <
1$
#820
0$
#821
b11 <
1$
#822
0$
#823
b100 <
1$
#824
0$
#825
b101 <
1$
#826
0$
#827
b110 <
1$
#828
0$
#829
b111 <
1$
#830
0$
#831
b0 <
b1 :
1$
#832
0$
#833
b1 <
0!
0=
1$
#834
0$
#835
b10 <
1$
#836
0$
#837
b11 <
1$
#838
0$
#839
b100 <
1$
#840
0$
#841
b101 <
1$
#842
0$
#843
b110 <
1$
#844
0$
#845
b111 <
1$
#846
0$
#847
b0 <
b10 :
1$
#848
0$
#849
b1 <
1$
#850
0$
#851
b10 <
1$
#852
0$
#853
b11 <
1$
#854
0$
#855
b100 <
1$
#856
0$
#857
b101 <
1$
#858
0$
#859
b110 <
1$
#860
0$
#861
b111 <
1$
#862
0$
#863
b0 <
b11 :
1$
#864
0$
#865
b1 <
1$
#866
0$
#867
b10 <
1$
#868
0$
#869
b11 <
1$
#870
0$
#871
b100 <
1$
#872
0$
#873
b101 <
1$
#874
0$
#875
b110 <
1$
#876
0$
#877
b111 <
1$
#878
0$
#879
b0 <
b100 :
1$
#880
0$
#881
b1 <
1$
#882
0$
#883
b10 <
1$
#884
0$
#885
b11 <
1$
#886
0$
#887
b100 <
1$
#888
0$
#889
b101 <
1$
#890
0$
#891
b110 <
1$
#892
0$
#893
b111 <
1$
#894
0$
#895
b0 <
b101 :
1$
#896
0$
#897
b1 <
1!
1=
1$
#898
0$
#899
b10 <
1$
#900
0$
#901
b11 <
1$
#902
0$
#903
b100 <
1$
#904
0$
#905
b101 <
1$
#906
0$
#907
b110 <
1$
#908
0$
#909
b111 <
1$
#910
0$
#911
b0 <
b110 :
1$
#912
0$
#913
b1 <
1$
#914
0$
#915
b10 <
1$
#916
0$
#917
b11 <
1$
#918
0$
#919
b100 <
1$
#920
0$
#921
b101 <
1$
#922
0$
#923
b110 <
1$
#924
0$
#925
b111 <
1$
#926
0$
#927
b0 <
b111 :
1$
#928
0$
#929
b1 <
0!
0=
1$
#930
0$
#931
b10 <
1$
#932
0$
#933
b11 <
1$
#934
0$
#935
b100 <
1$
#936
0$
#937
b101 <
1$
#938
0$
#939
b110 <
1$
#940
0$
#941
b111 <
1$
#942
0$
#943
b0 <
b11 >
1$
#944
0$
#945
b1 <
1!
1=
1$
#946
0$
#947
b10 <
1$
#948
0$
#949
b11 <
1$
#950
0$
#951
b100 <
1$
#952
0$
#953
b101 <
1$
#954
0$
#955
b110 <
1$
#956
0$
#957
b111 <
1$
#958
0$
#959
b0 <
b1 >
b101 ;
1$
#960
0$
#961
b1 <
0!
0=
1$
#962
0$
#963
b10 <
1$
#964
0$
#965
b11 <
1$
#966
0$
#967
b100 <
1$
#968
0$
#969
b101 <
1$
#970
0$
#971
b110 <
1$
#972
0$
#973
b111 <
1$
#974
0$
#975
b0 <
b0 :
b1111001 5
b10 >
1$
#976
0$
#977
b1 <
1!
1=
1$
#978
0$
#979
b10 <
1$
#980
0$
#981
b11 <
1$
#982
0$
#983
b100 <
1$
#984
0$
#985
b101 <
1$
#986
0$
#987
b110 <
1$
#988
0$
#989
b111 <
1$
#990
0$
#991
b0 <
b1 :
1$
#992
0$
#993
b1 <
0!
0=
1$
#994
0$
#995
b10 <
1$
#996
0$
#997
b11 <
1$
#998
0$
#999
b100 <
1$
#1000
0$
#1001
b101 <
1$
#1002
0$
#1003
b110 <
1$
#1004
0$
#1005
b111 <
1$
#1006
0$
#1007
b0 <
b10 :
1$
#1008
0$
#1009
b1 <
1$
#1010
0$
#1011
b10 <
1$
#1012
0$
#1013
b11 <
1$
#1014
0$
#1015
b100 <
1$
#1016
0$
#1017
b101 <
1$
#1018
0$
#1019
b110 <
1$
#1020
0$
#1021
b111 <
1$
#1022
0$
#1023
b0 <
b11 :
1$
#1024
0$
#1025
b1 <
1!
1=
1$
#1026
0$
#1027
b10 <
1$
#1028
0$
#1029
b11 <
1$
#1030
0$
#1031
b100 <
1$
#1032
0$
#1033
b101 <
1$
#1034
0$
#1035
b110 <
1$
#1036
0$
#1037
b111 <
1$
#1038
0$
#1039
b0 <
b100 :
1$
#1040
0$
#1041
b1 <
1$
#1042
0$
#1043
b10 <
1$
#1044
0$
#1045
b11 <
1$
#1046
0$
#1047
b100 <
1$
#1048
0$
#1049
b101 <
1$
#1050
0$
#1051
b110 <
1$
#1052
0$
#1053
b111 <
1$
#1054
0$
#1055
b0 <
b101 :
1$
#1056
0$
#1057
b1 <
1$
#1058
0$
#1059
b10 <
1$
#1060
0$
#1061
b11 <
1$
#1062
0$
#1063
b100 <
1$
#1064
0$
#1065
b101 <
1$
#1066
0$
#1067
b110 <
1$
#1068
0$
#1069
b111 <
1$
#1070
0$
#1071
b0 <
b110 :
1$
#1072
0$
#1073
b1 <
1$
#1074
0$
#1075
b10 <
1$
#1076
0$
#1077
b11 <
1$
#1078
0$
#1079
b100 <
1$
#1080
0$
#1081
b101 <
1$
#1082
0$
#1083
b110 <
1$
#1084
0$
#1085
b111 <
1$
#1086
0$
#1087
b0 <
b111 :
1$
#1088
0$
#1089
b1 <
0!
0=
1$
#1090
0$
#1091
b10 <
1$
#1092
0$
#1093
b11 <
1$
#1094
0$
#1095
b100 <
1$
#1096
0$
#1097
b101 <
1$
#1098
0$
#1099
b110 <
1$
#1100
0$
#1101
b111 <
1$
#1102
0$
#1103
b0 <
b11 >
1$
#1104
0$
#1105
b1 <
1!
1=
1$
#1106
0$
#1107
b10 <
1$
#1108
0$
#1109
b11 <
1$
#1110
0$
#1111
b100 <
1$
#1112
0$
#1113
b101 <
1$
#1114
0$
#1115
b110 <
1$
#1116
0$
#1117
b111 <
1$
#1118
0$
#1119
b0 <
b1 >
b110 ;
1$
#1120
0$
#1121
b1 <
0!
0=
1$
#1122
0$
#1123
b10 <
1$
#1124
0$
#1125
b11 <
1$
#1126
0$
#1127
b100 <
1$
#1128
0$
#1129
b101 <
1$
#1130
0$
#1131
b110 <
1$
#1132
0$
#1133
b111 <
1$
#1134
0$
#1135
b0 <
b0 :
b100000 5
b10 >
1$
#1136
0$
#1137
b1 <
1$
#1138
0$
#1139
b10 <
1$
#1140
0$
#1141
b11 <
1$
#1142
0$
#1143
b100 <
1$
#1144
0$
#1145
b101 <
1$
#1146
0$
#1147
b110 <
1$
#1148
0$
#1149
b111 <
1$
#1150
0$
#1151
b0 <
b1 :
1$
#1152
0$
#1153
b1 <
1$
#1154
0$
#1155
b10 <
1$
#1156
0$
#1157
b11 <
1$
#1158
0$
#1159
b100 <
1$
#1160
0$
#1161
b101 <
1$
